YMLEditor/data_manager.py
YMLEditor/item_widget.py
YMLEditor/settings_widget.py
YMLEditor/structured_text.py
YMLEditor/yaml_config.py
YMLEditor/yaml_reader.py
docs/source/conf.py
ymleditor-1.1.dist-info/licenses/LICENSE
ymleditor-1.1.dist-info/METADATA
ymleditor-1.1.dist-info/WHEEL
ymleditor-1.1.dist-info/top_level.txt
ymleditor-1.1.dist-info/RECORD
