Metadata-Version: 2.4
Name: YMLEditor
Version: 1.1
Summary: YMLEditor is a package for quickly creating editors for simple YAML configuration files.
Author: corb
License: Copyright 2025 corb555
Project-URL: Repository, https://github.com/corb555/YMLEditor
Keywords: YAML,configuration,editor
Classifier: Intended Audience :: Developers
Classifier: Topic :: Scientific/Engineering :: GIS
Classifier: Programming Language :: Python :: 3.8
Classifier: Programming Language :: Python :: 3.9
Classifier: Programming Language :: Python :: 3.10
Classifier: Programming Language :: Python :: 3.11
Classifier: Operating System :: POSIX :: Linux
Classifier: Operating System :: MacOS
Requires-Python: >=3.8
License-File: LICENSE
Requires-Dist: PyYAML>=6.0.1
Provides-Extra: pyqt
Requires-Dist: PyQt6>=6.6.1; extra == "pyqt"
Provides-Extra: pyside
Requires-Dist: PySide6>=6.6.0; extra == "pyside"
Provides-Extra: testing
Requires-Dist: pytest>=7.0; extra == "testing"
Requires-Dist: pytest-cov; extra == "testing"
Dynamic: license-file
